medcam3d/__init__.py
medcam3d/activations_and_gradients.py
medcam3d/base_medcam3d.py
medcam3d/grad_cam3d.py
medcam3d-0.0.4.dist-info/LICENSE
medcam3d-0.0.4.dist-info/METADATA
medcam3d-0.0.4.dist-info/WHEEL
medcam3d-0.0.4.dist-info/top_level.txt
medcam3d-0.0.4.dist-info/RECORD
