Metadata-Version: 2.1
Name: medcam3d
Version: 0.0.4
Summary: CAM for 3D medical image networks
Home-page: https://github.com/Jingnan-Jia/medcam3d
Author: Jingnan Jia
Author-email: jiajingnan2222@gmail.com
Project-URL: Bug Tracker, https://github.com/Jingnan-Jia/medcam3d/issues
Classifier: Programming Language :: Python :: 3
Classifier: License :: OSI Approved :: MIT License
Classifier: Operating System :: OS Independent
Requires-Python: >=3.6
License-File: LICENSE
Requires-Dist: numpy
Requires-Dist: Pillow
Requires-Dist: torch (>=1.7.1)
Requires-Dist: torchvision (>=0.8.2)
Requires-Dist: ttach
Requires-Dist: tqdm
Requires-Dist: opencv-python
Requires-Dist: matplotlib
Requires-Dist: scikit-learn
